denomagics/__init__.py
denomagics/denomagics.py
denomagics-1.1.15.dist-info/METADATA
denomagics-1.1.15.dist-info/WHEEL
denomagics-1.1.15.dist-info/top_level.txt
denomagics-1.1.15.dist-info/RECORD
